spcache/__init__.py
spcache/__main__.py
spcache/cli.py
spcache/detect.py
spcache/env.py
spcache-1.0.1.dist-info/LICENSE
spcache-1.0.1.dist-info/METADATA
spcache-1.0.1.dist-info/WHEEL
spcache-1.0.1.dist-info/entry_points.txt
spcache-1.0.1.dist-info/RECORD
